MANIFEST.in
README.rst
setup.cfg
setup.py
bloxby/__init__.py
bloxby/admin.py
bloxby/apps.py
bloxby/functions.py
bloxby/generics.py
bloxby/managers.py
bloxby/models.py
bloxby/packages.py
bloxby/querysets.py
bloxby/urls.py
bloxby/users.py
bloxby/utils.py
bloxby/views.py
bloxby/ftp/__init__.py
bloxby/ftp/admin.py
bloxby/ftp/apps.py
bloxby/ftp/authorizers.py
bloxby/ftp/filesystems.py
bloxby/ftp/handlers.py
bloxby/ftp/models.py
bloxby/ftp/server.py
bloxby/ftp/urls.py
bloxby/ftp/views.py
bloxby/ftp/migrations/0001_initial.py
bloxby/ftp/migrations/__init__.py
bloxby/migrations/0001_initial.py
bloxby/migrations/0002_page_template_templateasset.py
bloxby/migrations/0003_auto_20200522_1520.py
bloxby/migrations/__init__.py
bloxby/templates/index.html
bloxby/templatetags/__init__.py
bloxby/templatetags/bloxby.py
django_bloxby.egg-info/PKG-INFO
django_bloxby.egg-info/SOURCES.txt
django_bloxby.egg-info/dependency_links.txt
django_bloxby.egg-info/not-zip-safe
django_bloxby.egg-info/requires.txt
django_bloxby.egg-info/top_level.txt