Metadata-Version: 1.1
Name: django-bloxby
Version: 0.0.46
Summary: A django application for bridging bloxby and your django software supporting User creation, package creation and autologin
Home-page: https://github.com/damey2011/django-bloxby
Author: Damilola Adeyemi
Author-email: adeyemidamilola3@gmail.com
License: MIT
Keywords: django-bloxby
Platform: UNKNOWN
Classifier: Development Status :: 3 - Alpha
Classifier: Framework :: Django :: 2.1
Classifier: Intended Audience :: Developers
Classifier: License :: OSI Approved :: BSD License
Classifier: Natural Language :: English
Classifier: Programming Language :: Python :: 2
Classifier: Programming Language :: Python :: 2.7
Classifier: Programming Language :: Python :: 3
Classifier: Programming Language :: Python :: 3.5
Classifier: Programming Language :: Python :: 3.6
